[{"s": "225-55-r18-leto-dlya-krossoverov", "t": "225 55 R18 лето: лучшие шины для кроссоверов и внедорожников", "i": "🔍", "c": "podbor-shin"}, {"s": "225-60-r17-na-kakie-mashiny-podkhodit", "t": "Шины 225 60 R17: полный список совместимых авто и нюансы монтажа", "i": "🔍", "c": "podbor-shin"}, {"s": "225-75-r16-bystritsa", "t": "Шины Быстрица 225 75 R16: обзор, характеристики и эксплуатация", "i": "🏷️", "c": "obzory-brendov"}, {"s": "225-mm-v-sm", "t": "225 мм в см: Таблица перевода и объяснение маркировки шин", "i": "📏", "c": "markirovka-i-razmery"}, {"s": "225-65-17-at", "t": "Шины 225 65 R17: Полный гид по выбору, характеристикам и эксплуатации", "i": "🔍", "c": "podbor-shin"}, {"s": "225-rezina-na-7j", "t": "Шина 225 на диск 7J: совместимость, допуски и нюансы установки", "i": "🔍", "c": "podbor-shin"}, {"s": "225-75r16c-kama-218", "t": "225 75r16c Кама-218: Характеристики, плюсы и эксплуатация грузовых шин", "i": "🚜", "c": "spetstekhnika-i-gruzoviki"}, {"s": "225-75-16-v-dyujmakh", "t": "Шина 225/75 R16 в дюймах: полный перевод размеров и расшифровка", "i": "📏", "c": "markirovka-i-razmery"}, {"s": "225-55-r17-runflat", "t": "Шины 225/55 R17 RunFlat: Полное руководство, плюсы и минусы", "i": "🔍", "c": "podbor-shin"}, {"s": "225-45-17-skolko-kachat", "t": "Давление в шинах 225/45 R17: оптимальные значения и ошибки", "i": "🎈", "c": "davlenie-i-balansirovka"}, {"s": "225-45-r17-leto-kupit", "t": "Летние шины 225 45 R17: как выбрать и купить лучшие модели", "i": "🔍", "c": "podbor-shin"}, {"s": "225-75-r16-v-dyujmakh-skolko", "t": "Перевод размера 225/75 R16 в дюймы: диаметр, ширина и посадочный диаметр", "i": "📏", "c": "markirovka-i-razmery"}, {"s": "225-65-r17-na-tiguan-2", "t": "Шины 225 65 R17 на VW Tiguan 2: Разбор, плюсы и минусы установки", "i": "🔍", "c": "podbor-shin"}, {"s": "225-65-17-na-tiguan", "t": "Шины 225/65 R17 на Volkswagen Tiguan: совместимость, размеры и выбор", "i": "🔍", "c": "podbor-shin"}, {"s": "22-nedelya-kakoj-mesyats-shiny", "t": "22 неделя беременности: какой месяц и выбор шин для автомобиля", "i": "🔍", "c": "podbor-shin"}, {"s": "225-50-16-leto-kupit", "t": "Шина 225/50 R16: Летний выбор, цены и лучшие модели", "i": "🔍", "c": "podbor-shin"}, {"s": "225-70-15-s-zimnie-shiny", "t": "Шины 225/70 R15: Полный гид по выбору и эксплуатации", "i": "🔍", "c": "podbor-shin"}, {"s": "225-45-17-kakoe-davlenie-kachat", "t": "Давление в шинах 225/45 R17: нормы для авто и сезонные отличия", "i": "🎈", "c": "davlenie-i-balansirovka"}, {"s": "225-40-r18-zima", "t": "Шины 225 40 R18 на зиму: полный гид по выбору и характеристикам", "i": "🔍", "c": "podbor-shin"}, {"s": "225-65-r17-na-kakikh-mashinakh", "t": "225 65 R17 на каких машинах: полный список авто и рекомендации", "i": "🔍", "c": "podbor-shin"}, {"s": "225-50-r18-leto", "t": "Шины 225/50 R18 лето: гид по выбору, лучшие модели и советы", "i": "🔍", "c": "podbor-shin"}, {"s": "225-45-18-zima-triangl", "t": "Шины 225 45 R18 Триангл: обзор зимних моделей, характеристики и выбор", "i": "🏷️", "c": "obzory-brendov"}, {"s": "225-50-17-zima-lipuchka", "t": "Шины 225/50 R17: Зимняя «липучка» — полный гид по выбору и эксплуатации", "i": "🔍", "c": "podbor-shin"}, {"s": "225-75-16-na-nivu", "t": "Шины 225/75 R16 на Ниву: совместимость, плюсы и минусы установки", "i": "🔍", "c": "podbor-shin"}, {"s": "225-70-16-v-dyujmakh", "t": "Шина 225/70 R16 в дюймах: ширина, высота и диаметр колеса", "i": "📏", "c": "markirovka-i-razmery"}, {"s": "22-dyujma-skolko-eto-v-santimetrakh", "t": "22 дюйма в сантиметрах: перевод диаметра дисков и шин", "i": "🛞", "c": "diski-i-kolpaki"}, {"s": "225-55-r17-vsesezonnye", "t": "225 55 R17 всесезонные шины: Как выбрать и эксплуатировать", "i": "🔍", "c": "podbor-shin"}, {"s": "225-70-r16-at", "t": "Шины 225/70 R16 All Terrain: Полный гид по выбору и эксплуатации", "i": "🔍", "c": "podbor-shin"}, {"s": "225-60-17-triangle", "t": "225 60 R17 треугольник: Точность нанесения и безопасность", "i": "📏", "c": "markirovka-i-razmery"}, {"s": "225-75-r16c-vsesezonnye", "t": "Шины 225 75 R16C: Рейтинг лучших всесезонных моделей для коммерции", "i": "🔍", "c": "podbor-shin"}, {"s": "225-i-215-rezina-raznitsa", "t": "225 или 215 ширина резины: в чем разница и что лучше выбрать?", "i": "📏", "c": "markirovka-i-razmery"}, {"s": "225-75-r16-na-nivu", "t": "Шины 225/75 R16 на Ниву: установка, плюсы, минусы и совместимость", "i": "🔍", "c": "podbor-shin"}, {"s": "225-70-r15c-leto", "t": "Шины 225/70 R15C лето: Полный гид по выбору и эксплуатации", "i": "🔍", "c": "podbor-shin"}, {"s": "225-75-r15-na-nivu", "t": "Шины 225/75 R15 на Ниву: обзор совместимости, плюсы и минусы", "i": "🔍", "c": "podbor-shin"}, {"s": "225-60-17-zimnie-shiny-neshipovannye", "t": "Зимние шины 225/60 R17 без шипов: выбор, обзор и особенности", "i": "🔍", "c": "podbor-shin"}, {"s": "225-45-r18-zima-shipy", "t": "Шипованная резина 225/45 R18: Топ-10 моделей и советы по выбору", "i": "🔍", "c": "podbor-shin"}, {"s": "225-45-18-zima", "t": "Шины 225 45 18 на зиму: Как выбрать и не прогадать с профилем", "i": "🔍", "c": "podbor-shin"}, {"s": "225-75-r16-at", "t": "Шины 225/75 R16 AT: Полный обзор, выбор и эксплуатация внедорожных покрышек", "i": "🔍", "c": "podbor-shin"}, {"s": "225-75-r16-v-dyujmakh", "t": "Шина 225 75 R16: размеры в дюймах и перевод параметров", "i": "📏", "c": "markirovka-i-razmery"}, {"s": "225-70-16-na-nivu", "t": "Шины 225/70 R16 на Ниву: совместимость, плюсы и нюансы установки", "i": "🔍", "c": "podbor-shin"}, {"s": "225-45-r17-skolko-kachat", "t": "Давление в шинах 225/45 R17: нормы, нюансы и таблица значений", "i": "🎈", "c": "davlenie-i-balansirovka"}, {"s": "225-55-17-vsesezonnye-shiny", "t": "Шины 225 55 R17: полный гид по выбору лучшей всесезонки", "i": "🔍", "c": "podbor-shin"}, {"s": "225-75-16-mt", "t": "Шины 225 75 16 МТ: гид по внедорожным покрышкам и установке", "i": "🔍", "c": "podbor-shin"}, {"s": "225-45-17-davlenie-v-shinakh", "t": "Давление в шинах 225 45 17: нормы, таблица и последствия ошибок", "i": "🎈", "c": "davlenie-i-balansirovka"}, {"s": "225-40-17-leto", "t": "Шины 225/40 R17 лето: гид по выбору, характеристикам и рейтингам", "i": "🔍", "c": "podbor-shin"}, {"s": "225-55-r16-leto", "t": "Шины 225 55 R16 летом: выбор, характеристики и лучшие модели", "i": "🔍", "c": "podbor-shin"}, {"s": "225-45-17-zimnyaya-rezina", "t": "Зимняя резина 225/45 R17: полный гайд по выбору и характеристикам", "i": "🔍", "c": "podbor-shin"}, {"s": "225mm-eto-skolko-sm", "t": "225 мм это сколько см: конвертация размера шин и дисков", "i": "📏", "c": "markirovka-i-razmery"}, {"s": "225-60-18-zimnie-shiny-neshipovannye-kupit", "t": "Купить зимние шины 225/60 R18 нешипованные: гид по выбору и рейтинг моделей", "i": "🔍", "c": "podbor-shin"}, {"s": "225-rezina-na-9j", "t": "225 резина на диск 9J: совместимость, последствия и рекомендации", "i": "🔍", "c": "podbor-shin"}, {"s": "225-45-17-zima-lipuchka", "t": "Зимняя липучка 225 45 17: Полный гид по выбору и лучшие модели", "i": "🔍", "c": "podbor-shin"}, {"s": "225-70-r15c-zima", "t": "Шины 225 70 R15C: Полный гид по выбору зимней резины для коммерции", "i": "🔍", "c": "podbor-shin"}, {"s": "225-55-18-kumho", "t": "Шины Kumho 225/55 R18: Обзор моделей, характеристики и выбор", "i": "🏷️", "c": "obzory-brendov"}, {"s": "225-65-17-shipy", "t": "Шипы для шин 225/65 R17: Выбор, установка и особенности эксплуатации", "i": "🔍", "c": "podbor-shin"}, {"s": "225-50-17-zimnyaya-rezina", "t": "Зимняя резина 225/50 R17: выбор, характеристики и лучшие модели", "i": "🔍", "c": "podbor-shin"}, {"s": "225-65-17-zimnie-shiny-lipuchka", "t": "Зимние шины 225 65 R17 липучка: Рейтинг, выбор и особенности", "i": "🔍", "c": "podbor-shin"}, {"s": "225-60-17-leto-dlya-krossoverov", "t": "Шины 225/60 R17 лето: Топ-моделей для кроссоверов и SUV", "i": "🔍", "c": "podbor-shin"}, {"s": "225-75-16-skolko-v-dyujmakh", "t": "Перевод размера 225/75 R16 в дюймы: полная расшифровка", "i": "📏", "c": "markirovka-i-razmery"}, {"s": "225-40-18-letnyaya-rezina", "t": "Летние шины 225/40 R18: выбор, характеристики и лучшие модели", "i": "🔍", "c": "podbor-shin"}, {"s": "225-45-18-zimnyaya-rezina", "t": "Зимняя резина 225/45 R18: выбор, характеристики и лучшие модели", "i": "🔍", "c": "podbor-shin"}, {"s": "225-55-18-zimnie-shiny-neshipovannye-kupit", "t": "Зимние шины 225 55 18 нешипованные: как выбрать и где купить", "i": "🔍", "c": "podbor-shin"}, {"s": "225-70-16-at", "t": "Шина 225/70 R16 AT: полный гид по выбору всесезонной резины", "i": "🔍", "c": "podbor-shin"}, {"s": "225-mm-skolko-sm", "t": "225 мм сколько см: Таблица перевода и применение в автошинах", "i": "🔍", "c": "podbor-shin"}, {"s": "225-45-18-leto", "t": "Шины 225 45 R18 лето: Полный гид по выбору и характеристикам", "i": "🔍", "c": "podbor-shin"}, {"s": "225-shirina-reziny-na-kakoj-disk", "t": "225 ширина резины на какой диск: полный гайд по совместимости", "i": "🛞", "c": "diski-i-kolpaki"}, {"s": "225-65-17-michelin", "t": "Шина Michelin размер 225 65 17: Обзор моделей, характеристики и выбор", "i": "🔍", "c": "podbor-shin"}, {"s": "225-55-r18-98v-rasshifrovka", "t": "225 55 R18 98V: полная расшифровка параметров шины и выбор резины", "i": "📏", "c": "markirovka-i-razmery"}, {"s": "225-65-17-nexen", "t": "Шины Nexen 225/65 R17: обзор моделей, характеристики и выбор", "i": "🔍", "c": "podbor-shin"}, {"s": "225-65-r17-leto-dlya-krossoverov", "t": "Летние шины 225 65 R17: Топ моделей для кроссоверов и внедорожников", "i": "🔍", "c": "podbor-shin"}, {"s": "225-70-r16-na-nivu", "t": "Шины 225/70 R16 на Ниву: совместимость, плюсы и минусы установки", "i": "🔍", "c": "podbor-shin"}, {"s": "225-40-18-zima-kupit", "t": "Шины 225 40 18 зима: Как выбрать, где купить и что учесть", "i": "🔍", "c": "podbor-shin"}, {"s": "225-50-r17-runflat-zima", "t": "Шины 225 50 R17 RunFlat: Полный гид по зимней эксплуатации", "i": "🔍", "c": "podbor-shin"}, {"s": "225-75-16-gryazevaya-rezina", "t": "Шины 225/75 R16: Лучшая грязевая резина для внедорожников", "i": "🔍", "c": "podbor-shin"}, {"s": "225-75-r16c-zima-neshipovannye", "t": "Зимние нешипованные шины 225/75 R16C: выбор и особенности", "i": "🔍", "c": "podbor-shin"}, {"s": "225-55-r17-davlenie-v-shinakh", "t": "Давление в шинах 225/55 R17: норма для авто и важные нюансы", "i": "🎈", "c": "davlenie-i-balansirovka"}, {"s": "225-55-18-zimnyaya-rezina-kupit", "t": "Зимняя резина 225/55 R18: рейтинг, выбор и цены", "i": "🔍", "c": "podbor-shin"}, {"s": "225-65-16s-zimnyaya-rezina", "t": "Шины 225/65 R16: Лучшая зимняя резина для кроссоверов", "i": "🔍", "c": "podbor-shin"}, {"s": "225-i-235-raznitsa-rezina", "t": "225 против 235: в чем разница шин, как выбрать и совместить", "i": "🔍", "c": "podbor-shin"}, {"s": "225-55-18-zima-shipy", "t": "Шипованная резина 225 55 18: Топ моделей и правила выбора", "i": "🔍", "c": "podbor-shin"}, {"s": "225-55-r19-zimnie-shipovannye", "t": "225 55 r19 зимние шипованные: Рейтинг, выбор и особенности", "i": "🔍", "c": "podbor-shin"}, {"s": "225-45-17-pirelli", "t": "Шины Pirelli 225/45 R17: обзор моделей, характеристики и выбор", "i": "🏷️", "c": "obzory-brendov"}, {"s": "225-70-r16-na-daster", "t": "Шины 225/70 R16 на Duster: обзор, совместимость и отзывы", "i": "🔍", "c": "podbor-shin"}, {"s": "22-radius-kolesa-v-santimetrakh", "t": "22 радиус колеса в сантиметрах: точный перевод и размеры шин", "i": "📏", "c": "markirovka-i-razmery"}, {"s": "225-65-16s-zimnyaya-rezina-shipy", "t": "Зимняя резина 225 65 R16 с шипами: Рейтинг, выбор и установка", "i": "🔍", "c": "podbor-shin"}, {"s": "225-65-18-zimnie-shiny-shipovannye-kupit", "t": "Купить шипованные шины 225 65 18: гид по выбору и цене", "i": "🔍", "c": "podbor-shin"}, {"s": "225-60-r18-diski", "t": "Шины 225/60 R18: Полный гид по выбору, размерам и эксплуатации", "i": "🔍", "c": "podbor-shin"}, {"s": "225-65-17-na-tiguan-2", "t": "Шины 225 65 R17 на VW Tiguan 2: полный разбор совместимости и характеристик", "i": "🔍", "c": "podbor-shin"}, {"s": "225-75-15-na-nivu", "t": "Шины 225/75 R15 на Ниву: плюсы, минусы и нюансы установки", "i": "🔍", "c": "podbor-shin"}, {"s": "225-60-17-continental", "t": "Шины Continental 225/60 R17: Полный гид по выбору и эксплуатации", "i": "🏷️", "c": "obzory-brendov"}, {"s": "225-60-18-zimnyaya-rezina", "t": "Выбор зимней резины 225 60 18: Топ моделей и советы по установке", "i": "🔍", "c": "podbor-shin"}, {"s": "225-65-r17-leto-yokohama", "t": "Летние шины Yokohama 225 65 R17: обзор моделей и выбор", "i": "🏷️", "c": "obzory-brendov"}, {"s": "225-60-r17-zima-shipy", "t": "Шипованная резина 225/60 R17: Топ моделей и секреты выбора", "i": "🔍", "c": "podbor-shin"}]