[{"s": "kak-chasto-menyat-pokryshki-na-velosipede", "t": "Как часто менять покрышки на велосипеде: признаки износа и сроки", "i": "🚲", "c": "velosipednye-shiny"}, {"s": "kak-chitayutsya-razmery-shin", "t": "Как читаются размеры шин: полная расшифровка маркировки", "i": "📏", "c": "markirovka-i-razmery"}, {"s": "kak-chitaetsya-razmer-shin-na-avtomobil", "t": "Как читать размер шин на автомобиле: расшифровка маркировки и параметры", "i": "📏", "c": "markirovka-i-razmery"}, {"s": "kak-chasto-menyat-shiny-avtomobilya", "t": "Как часто менять шины: сроки, пробег и признаки износа", "i": "❄️", "c": "sezonnaya-smena"}, {"s": "kak-chasto-menyat-zimnyuyu-rezinu", "t": "Как часто менять зимнюю резину: сроки, износ и признаки замены", "i": "❄️", "c": "sezonnaya-smena"}, {"s": "kak-chasto-menyat-zimnyuyu-rezinu-na-novuyu", "t": "Когда менять зимнюю резину: реальный срок службы и признаки износа", "i": "❄️", "c": "sezonnaya-smena"}, {"s": "kak-chinyat-mashiny-igrushechnye", "t": "Ремонт игрушечных машин: как починить электронику, кузов и колеса", "i": "📁", "c": "drugoe"}, {"s": "kak-chasto-nado-menyat-rezinu-na-avtomobile", "t": "Как часто менять резину на авто: график, износ и безопасность", "i": "❄️", "c": "sezonnaya-smena"}, {"s": "kak-chitaetsya-razmer-shin", "t": "Как читать размер шин: расшифровка маркировки и подбор", "i": "📏", "c": "markirovka-i-razmery"}, {"s": "kak-chasto-trenirovatsya-na-kurse", "t": "Как часто тренироваться на курсе: график, отдых и результаты", "i": "📁", "c": "drugoe"}, {"s": "kak-chasto-nado-menyat-shiny-na-avtomobile", "t": "Как часто менять шины: сроки, износ и правила замены резины", "i": "❄️", "c": "sezonnaya-smena"}, {"s": "kak-chasto-nado-menyat-diski-na-kolesakh", "t": "Как часто менять тормозные диски: признаки износа и сроки замены", "i": "🛞", "c": "diski-i-kolpaki"}, {"s": "kak-chasto-nuzhno-menyat-rezinu-na-mashine", "t": "Как часто менять резину на машине: нормы, износ и сроки службы", "i": "❄️", "c": "sezonnaya-smena"}, {"s": "kak-chasto-nuzhno-menyat-letnyuyu-rezinu-na-mashine", "t": "Когда менять летнюю резину: сроки, температура и износ шин", "i": "❄️", "c": "sezonnaya-smena"}, {"s": "kak-chasto-nuzhno-menyat-letnyuyu-rezinu", "t": "Как часто менять летнюю резину: сроки, износ и признаки замены", "i": "❄️", "c": "sezonnaya-smena"}, {"s": "kak-chasto-nuzhno-menyat-shiny-na-avtomobile-na-novye", "t": "Как часто менять шины на автомобиле: сроки, пробег и износ", "i": "❄️", "c": "sezonnaya-smena"}, {"s": "kak-chasto-menyat-rezinu-na-avto", "t": "Как часто менять резину на авто: сроки, износ и правила", "i": "❄️", "c": "sezonnaya-smena"}, {"s": "kak-chasto-menyat-rezinu", "t": "Как часто менять резину: сроки, износ и правила замены автошин", "i": "❄️", "c": "sezonnaya-smena"}, {"s": "kak-chinyat-prokol-kolesa", "t": "Как чинят прокол колеса: способы ремонта от шиномонтажа", "i": "🔧", "c": "remont-i-vulkanizatsiya"}, {"s": "kak-chasto-nado-menyat-pokryshki", "t": "Как часто менять шины: регламент, износ и сезонность", "i": "❄️", "c": "sezonnaya-smena"}]